{
  "vine_boom": {
    "subtitle": "subtitles.item.copper_horn.play",
    "sounds": [
        "kahmod:custom/vine_boom"
    ]
  },
  "yippie": {
    "subtitle": "subtitles.item.copper_horn.play",
    "sounds": [
      "kahmod:custom/yippie"
    ]
  },
  "sus": {
    "subtitle": "subtitles.item.copper_horn.play",
    "sounds": [
      "kahmod:custom/sus"
    ]
  },
  "music_disc.amogus": {
    "sounds": [
      {
        "name":"kahmod:records/amogus",
        "stream": true
      }
    ]
  },
  "music_disc.mrbigshot": {
    "sounds": [
      {
        "name":"kahmod:records/mrbigshot",
        "stream": true,
        "volume": 0.7
      }
    ]
  }
}

