{
  "parent": "kahmod:kahmod/obtain_yellow_concrete",
  "criteria": {
    "powder_snow": {
      "conditions": {
        "items": [
          {
            "items": [
              "minecraft:powder_snow_bucket"
            ]
          }
        ]
      },
      "trigger": "minecraft:inventory_changed"
    }
  },
  "display": {
    "announce_to_chat": true,
    "description": {
      "translate": "advancements.kahmod.obtain_powder_snow.description"
    },
    "frame": "task",
    "hidden": false,
    "icon": {
      "item": "minecraft:powder_snow_bucket"
    },
    "show_toast": true,
    "title": {
      "translate": "advancements.kahmod.obtain_powder_snow.title"
    }
  },
  "requirements": [
    [
      "powder_snow"
    ]
  ]
}